pyzwoasi/__init__.py
pyzwoasi/camera.py
pyzwoasi/pyzwoasi.py
pyzwoasi/lib/Linux/x64/libASICamera2.so.1.37
pyzwoasi/lib/Linux/x86/libASICamera2.so.1.37
pyzwoasi/lib/MacOS/libASICamera2.dylib.1.37
pyzwoasi/lib/Windows/x64/ASICamera2.dll
pyzwoasi/lib/Windows/x86/ASICamera2.dll
pyzwoasi-0.2.2.dist-info/licenses/LICENSE.txt
pyzwoasi-0.2.2.dist-info/METADATA
pyzwoasi-0.2.2.dist-info/WHEEL
pyzwoasi-0.2.2.dist-info/top_level.txt
pyzwoasi-0.2.2.dist-info/RECORD
