Metadata-Version: 2.4
Name: pyzwoasi
Version: 0.2.2
Summary: Python binding for the ZWO ASI SDK library
Author-email: Francois Margall <fr.margall@proton.me>
Project-URL: Repository, https://github.com/fmargall/pyzwoasi.git
Keywords: binding,zwo,asi,sdk,wrapper,camera,astronomy
Classifier: Development Status :: 3 - Alpha
Classifier: License :: OSI Approved :: MIT License
Classifier: Operating System :: Microsoft :: Windows
Classifier: Operating System :: POSIX :: Linux
Classifier: Operating System :: MacOS :: MacOS X
License-File: LICENSE.txt
Requires-Dist: numpy
Requires-Dist: opencv-python
Dynamic: license-file
